xlnumba/__init__.py
xlnumba/ast.py
xlnumba/compiler.py
xlnumba/compiler_frame.py
xlnumba/excel_reference.py
xlnumba/exceptions.py
xlnumba/execution.py
xlnumba/logger.py
xlnumba/shape.py
xlnumba/shunting_yards.py
xlnumba/special_functions.py
xlnumba/excel_functions/__init__.py
xlnumba/excel_functions/function_details.py
xlnumba/excel_functions/information.py
xlnumba/excel_functions/logical.py
xlnumba/excel_functions/lookup.py
xlnumba/excel_functions/mathematical.py
xlnumba/excel_functions/random.py
xlnumba/excel_functions/special.py
xlnumba/excel_functions/statistical.py
xlnumba/excel_functions/text.py
xlnumba/excel_functions/user_functions.py
xlnumba/nodes/__init__.py
xlnumba/nodes/array.py
xlnumba/nodes/binary_ops.py
xlnumba/nodes/function.py
xlnumba/nodes/io.py
xlnumba/nodes/literal.py
xlnumba/nodes/node.py
xlnumba/nodes/random.py
xlnumba/optimizations/__init__.py
xlnumba/optimizations/array_inplace.py
xlnumba/optimizations/collapse_literals.py
xlnumba/optimizations/lazy_conditional.py
xlnumba/optimizations/merge_array.py
xlnumba-0.1.0.dist-info/METADATA
xlnumba-0.1.0.dist-info/WHEEL
xlnumba-0.1.0.dist-info/licenses/LICENSE
xlnumba-0.1.0.dist-info/RECORD
