Metadata-Version: 2.4
Name: xlnumba
Version: 0.1.0
Summary: A package for converting excel files to Numba optimized python code
License-Expression: MIT
License-File: LICENSE
Keywords: excel,numba,optimization
Classifier: Development Status :: 4 - Beta
Classifier: Intended Audience :: Developers
Classifier: Programming Language :: Python :: 3
Classifier: Programming Language :: Python :: 3.12
Classifier: Topic :: Software Development :: Build Tools
Requires-Python: >=3.12
Requires-Dist: astor>=0.8.1
Requires-Dist: numba>=0.59.0
Requires-Dist: numpy>=1.26.4
Requires-Dist: openpyxl>=3.1.2
Requires-Dist: scipy>=1.15.2
